Metadata-Version: 1.0
Name: testlpsdk2
Version: 3.0.0
Summary: Lyrebird Vocal Avatar SDK for Python
Home-page: https://github.com/Momoumar/testlpsdk
Author: The Lyrebird Team
Author-email: support@lyrebird.ai
License: UNKNOWN
Keywords: LYREBIRD-AI,TTS,AI,VOCAL AVATAR,VOICE
Platform: UNKNOWN
